trader/__init__.py
trader/start.py
trader/data/__init__.py
trader/data/get_alpha_vantage.py
trader/data/get_yfinance.py
trader_python-0.0.3.dist-info/METADATA
trader_python-0.0.3.dist-info/WHEEL
trader_python-0.0.3.dist-info/top_level.txt
trader_python-0.0.3.dist-info/RECORD
